fastapi_elasticsearch/__init__.py
fastapi_elasticsearch/api.py
fastapi_elasticsearch-0.8.2.dist-info/METADATA
fastapi_elasticsearch-0.8.2.dist-info/WHEEL
fastapi_elasticsearch-0.8.2.dist-info/top_level.txt
fastapi_elasticsearch-0.8.2.dist-info/RECORD
