Metadata-Version: 2.1
Name: fastapi-elasticsearch
Version: 0.8.2
Summary: Query Utility for Elasticsearch
Home-page: https://github.com/euler-io/fastapi-elasticsearch
License: LGPL-2.1 License
Requires-Dist: fastapi ==0.95.2
Requires-Dist: python-forge ==18.6.0
